m1_cis/__init__.py
m1_cis/clip_handler.py
m1_cis/gemini_handler.py
m1_cis/main.py
m1_cis/tests.py
m1_cis/types.py
m1_cis-0.2.0.dist-info/METADATA
m1_cis-0.2.0.dist-info/WHEEL
m1_cis-0.2.0.dist-info/licenses/LICENSE
m1_cis-0.2.0.dist-info/RECORD
