Metadata-Version: 2.4
Name: m1-cis
Version: 0.2.0
Summary: Context Image Search Utility
Project-URL: Homepage, https://github.com/M1chol/m1-cis
Project-URL: Issues, https://github.com/M1chol/m1-cis/issues
Author-email: Michał Kozłowski <m1chol@proton.me>
License-Expression: Apache-2.0
License-File: LICENSE
Classifier: Development Status :: 3 - Alpha
Classifier: Operating System :: OS Independent
Classifier: Programming Language :: Python :: 3
Classifier: Topic :: Internet :: WWW/HTTP :: Indexing/Search
Requires-Python: >=3.9
Requires-Dist: google-genai>=1.38.0
Requires-Dist: pillow>=11.3.0
Requires-Dist: pydantic>=2.11.9
Requires-Dist: requests>=2.32.5
Requires-Dist: torch>=2.8.0
Requires-Dist: torchvision>=0.23.0
Requires-Dist: transformers>=4.56.1
